MANIFEST.in
README.md
README.rst
reqs.txt
setup.cfg
setup.py
matchers/__init__.py
matchers.egg-info/PKG-INFO
matchers.egg-info/SOURCES.txt
matchers.egg-info/dependency_links.txt
matchers.egg-info/requires.txt
matchers.egg-info/top_level.txt