Metadata-Version: 1.1
Name: matchers
Version: 0.22
Summary: Collection of highly reusable hamcrest matchers
Home-page: https://github.com/grupotaric/matchers
Author: Taric S.A.
Author-email: appregs@taric.es
License: UNKNOWN
Download-URL: https://github.com/grupotaric/matchers/tags
Platform: UNKNOWN
Classifier: Programming Language :: Python
Classifier: Topic :: Software Development :: Testing
Classifier: Operating System :: OS Independent
Classifier: Intended Audience :: Developers
